gpt_command_line-0.4.3.dist-info/licenses/LICENSE
gptcli/__init__.py
gptcli/assistant.py
gptcli/cli.py
gptcli/completion.py
gptcli/composite.py
gptcli/config.py
gptcli/cost.py
gptcli/gpt.py
gptcli/logging_utils.py
gptcli/session.py
gptcli/shell.py
gptcli/providers/__init__.py
gptcli/providers/anthropic.py
gptcli/providers/azure_openai.py
gptcli/providers/cohere.py
gptcli/providers/google.py
gptcli/providers/llama.py
gptcli/providers/openai.py
gpt_command_line-0.4.3.dist-info/METADATA
gpt_command_line-0.4.3.dist-info/WHEEL
gpt_command_line-0.4.3.dist-info/entry_points.txt
gpt_command_line-0.4.3.dist-info/top_level.txt
gpt_command_line-0.4.3.dist-info/RECORD
