Metadata-Version: 2.4
Name: gpt-command-line
Version: 0.4.3
Summary: Command-line interface for ChatGPT and Claude
Author-email: Val Kharitonov <val@kharvd.com>
License: Copyright (c) 2023 by Val Kharitonov
Project-URL: Homepage, https://github.com/kharvd/gpt-cli
Keywords: cli,command-line,assistant,openai,claude,cohere,gpt-3,gpt-4,llm,chatgpt,gpt-cli,anthropic,gpt-client,anthropic-claude
Classifier: Development Status :: 4 - Beta
Classifier: Environment :: Console
Classifier: Intended Audience :: Developers
Classifier: Intended Audience :: End Users/Desktop
Classifier: Intended Audience :: Science/Research
Classifier: License :: OSI Approved :: MIT License
Classifier: Topic :: Scientific/Engineering :: Artificial Intelligence
Requires-Python: <3.13,>=3.9
License-File: LICENSE
Requires-Dist: anthropic~=0.47.1
Requires-Dist: attrs~=25.1.0
Requires-Dist: black~=25.1.0
Requires-Dist: cohere~=5.13.12
Requires-Dist: google-genai~=1.10.0
Requires-Dist: openai~=1.64.0
Requires-Dist: prompt-toolkit~=3.0.50
Requires-Dist: pytest~=8.3.4
Requires-Dist: PyYAML~=6.0.2
Requires-Dist: rich~=13.9.4
Requires-Dist: typing_extensions~=4.12.2
Provides-Extra: llama
Requires-Dist: llama-cpp-python==0.2.74; extra == "llama"
Dynamic: license-file
